LICENSE.TXT
pyevolve_ex10_g1dbinstr.py
pyevolve_ex11_allele.py
pyevolve_ex12_tsp.py
pyevolve_ex13_sphere.py
pyevolve_ex14_ackley.py
pyevolve_ex15_rosenbrock.py
pyevolve_ex1_simple.py
pyevolve_ex2_realgauss.py
pyevolve_ex3_schaffer.py
pyevolve_ex4_sigmatrunc.py
pyevolve_ex5_callback.py
pyevolve_ex6_dbadapter.py
pyevolve_ex7_rastringin.py
pyevolve_ex8_gauss_int.py
pyevolve_ex9_g2dlist.py
pyevolve_graph.py
pyevolve_profiler.py
setup.py
Pyevolve.egg-info/PKG-INFO
Pyevolve.egg-info/SOURCES.txt
Pyevolve.egg-info/dependency_links.txt
Pyevolve.egg-info/top_level.txt
docs/api-0.4.pdf
docs/epydoc.conf
docs/logo.psd
docs/todo_ideas.txt
docs/source/conf.py
docs/source/contact.rst
docs/source/examples.rst
docs/source/faq.rst
docs/source/getstarted.rst
docs/source/graphs.rst
docs/source/index.rst
docs/source/intro.rst
docs/source/license.rst
docs/source/module_allele.rst
docs/source/module_const.rst
docs/source/module_crossovers.rst
docs/source/module_dbadapters.rst
docs/source/module_functionslot.rst
docs/source/module_g1dbinarystring.rst
docs/source/module_g1dlist.rst
docs/source/module_g2dlist.rst
docs/source/module_genomebase.rst
docs/source/module_gpopulation.rst
docs/source/module_gsimplega.rst
docs/source/module_initializators.rst
docs/source/module_interaction.rst
docs/source/module_mutators.rst
docs/source/module_pyevolve.rst
docs/source/module_scaling.rst
docs/source/module_selectors.rst
docs/source/module_statistics.rst
docs/source/module_util.rst
docs/source/modules.rst
docs/source/sphinx06_code_patch.py
docs/source/.static/default_patch.css
docs/source/.static/delicious_icon.png
docs/source/.static/digg_icon.png
docs/source/.static/feed_icon.png
docs/source/.static/pyevolve.css
docs/source/.templates/layout.html
docs/source/imgs/ex1equation.png
docs/source/imgs/ex_12_tsp_result.png
docs/source/imgs/graph_1_ex1.png
docs/source/imgs/graph_2_ex1.png
docs/source/imgs/graph_3_ex1.png
docs/source/imgs/graph_4_ex1.png
docs/source/imgs/graph_5_ex1.png
docs/source/imgs/graph_6_ex1.png
docs/source/imgs/graph_7_ex1.png
docs/source/imgs/graph_8_ex1.png
docs/source/imgs/graph_8_ex1_spec.png
