Metadata-Version: 1.0
Name: Pyevolve
Version: 0.5
Summary: A complete python genetic algorithm framework
Home-page: http://pyevolve.sourceforge.net/
Author: Christian S. Perone
Author-email: christian.perone@gmail.com
License: PSF
Download-URL: https://sourceforge.net/project/showfiles.php?group_id=251160
Keywords: genetic algorithm algorithms framework library python
Platform: UNKNOWN
